Workbook

Sheet 70
A1: NOMBRE | B1: DNI | C1: LUGAR PAGO | D1: ESCUELA | E1: CONTROL | F1: CARGO | G1: TOTAL HAB SIN APORTE | H1: TOTAL HAB CON APORTE | I1: TOTAL HABER | J1: TOTAL DESCUENTOS | K1: PLANTA | L1: SALARIO | M1: TOTAL LIQUIDO | N1: FECHA INGRESO | O1: CUIL | P1: SEXO | Q1: REGISTRO
A2: =MID(Q2,Hoja2!$D$2,Hoja2!$F$2) -> LLANOS,MARGARITA NANCY | B2: =MID(Q2,Hoja2!$D$3,Hoja2!$B$3) -> 17066586 | C2: =MID(Q2,Hoja2!$D$4,Hoja2!$B$4) -> 38161 | D2: =MID(Q2,Hoja2!$D$5,Hoja2!$B$5) -> 00874 | E2: =MID(Q2,Hoja2!$D$6,Hoja2!$B$6) -> 38000131 | F2: =MID(Q2,Hoja2!$D$7,Hoja2!$B$7) -> 060098 | G2: =MID(Q2,Hoja2!$D$8,Hoja2!$B$8)/100 -> 2309.02 | H2: =MID(Q2,Hoja2!$D$9,Hoja2!$B$9)/100 -> 14462.97 | I2: =MID(Q2,Hoja2!$D$10,Hoja2!$B$10)/100 -> 16771.99 | J2: =MID(Q2,Hoja2!$D$11,Hoja2!$B$11)/100 -> 2603.34 | K2: =MID(Q2,Hoja2!$D$12,Hoja2!$B$12) -> D | L2: =MID(Q2,Hoja2!$D$13,Hoja2!$B$13) -> 00000000000000 | M2: =MID(Q2,Hoja2!$D$14,Hoja2!$B$14)/100 -> 14168.65 | N2: =MID(Q2,Hoja2!$D$15,Hoja2!$B$15) -> 180904 | O2: =MID(Q2,Hoja2!$D$16,Hoja2!$B$16) -> 23170665864 | P2: =MID(Q2,Hoja2!$D$17,Hoja2!$B$17) -> M | Q2: LLANOS,MARGARITA NANCY 1706658638161008743800013106009800000000230902000000014462970000000167719900000000260334D000000000000000000000141686518090423170665864M00000000000000
A3: =MID(Q3,Hoja2!$D$2,Hoja2!$F$2) -> CARABAJAL NORMA GRACIELA | B3: =MID(Q3,Hoja2!$D$3,Hoja2!$B$3) -> 25276017 | C3: =MID(Q3,Hoja2!$D$4,Hoja2!$B$4) -> 38242 | D3: =MID(Q3,Hoja2!$D$5,Hoja2!$B$5) -> 09687 | E3: =MID(Q3,Hoja2!$D$6,Hoja2!$B$6) -> 38000173 | F3: =MID(Q3,Hoja2!$D$7,Hoja2!$B$7) -> 060098 | G3: =MID(Q3,Hoja2!$D$8,Hoja2!$B$8)/100 -> 2239.73 | H3: =MID(Q3,Hoja2!$D$9,Hoja2!$B$9)/100 -> 13448.63 | I3: =MID(Q3,Hoja2!$D$10,Hoja2!$B$10)/100 -> 15688.36 | J3: =MID(Q3,Hoja2!$D$11,Hoja2!$B$11)/100 -> 2420.75 | K3: =MID(Q3,Hoja2!$D$12,Hoja2!$B$12) -> D | L3: =MID(Q3,Hoja2!$D$13,Hoja2!$B$13) -> 00000000000000 | M3: =MID(Q3,Hoja2!$D$14,Hoja2!$B$14)/100 -> 13267.61 | N3: =MID(Q3,Hoja2!$D$15,Hoja2!$B$15) -> 170108 | O3: =MID(Q3,Hoja2!$D$16,Hoja2!$B$16) -> 27252760178 | P3: =MID(Q3,Hoja2!$D$17,Hoja2!$B$17) -> M | Q3: CARABAJAL NORMA GRACIELA 2527601738242096873800017306009800000000223973000000013448630000000156883600000000242075D000000000000000000000132676117010827252760178M00000000000000
A4: =MID(Q4,Hoja2!$D$2,Hoja2!$F$2) -> RODRIGUEZ,SILVIA NOEMI | B4: =MID(Q4,Hoja2!$D$3,Hoja2!$B$3) -> 25470711 | C4: =MID(Q4,Hoja2!$D$4,Hoja2!$B$4) -> 38161 | D4: =MID(Q4,Hoja2!$D$5,Hoja2!$B$5) -> 00592 | E4: =MID(Q4,Hoja2!$D$6,Hoja2!$B$6) -> 38000262 | F4: =MID(Q4,Hoja2!$D$7,Hoja2!$B$7) -> 060098 | G4: =MID(Q4,Hoja2!$D$8,Hoja2!$B$8)/100 -> 2031.88 | H4: =MID(Q4,Hoja2!$D$9,Hoja2!$B$9)/100 -> 10405.59 | I4: =MID(Q4,Hoja2!$D$10,Hoja2!$B$10)/100 -> 12437.47 | J4: =MID(Q4,Hoja2!$D$11,Hoja2!$B$11)/100 -> 1977.07 | K4: =MID(Q4,Hoja2!$D$12,Hoja2!$B$12) -> D | L4: =MID(Q4,Hoja2!$D$13,Hoja2!$B$13) -> 00000000000000 | M4: =MID(Q4,Hoja2!$D$14,Hoja2!$B$14)/100 -> 10460.4 | N4: =MID(Q4,Hoja2!$D$15,Hoja2!$B$15) -> 150611 | O4: =MID(Q4,Hoja2!$D$16,Hoja2!$B$16) -> 27254707118 | P4: =MID(Q4,Hoja2!$D$17,Hoja2!$B$17) -> M | Q4: RODRIGUEZ,SILVIA NOEMI 2547071138161005923800026206009800000000203188000000010405590000000124374700000000197707D000000000000000000000104604015061127254707118M00000000000000
A5: =MID(Q5,Hoja2!$D$2,Hoja2!$F$2) -> TORRES ROSALIA VERONICA | B5: =MID(Q5,Hoja2!$D$3,Hoja2!$B$3) -> 27283990 | C5: =MID(Q5,Hoja2!$D$4,Hoja2!$B$4) -> 38242 | D5: =MID(Q5,Hoja2!$D$5,Hoja2!$B$5) -> 09134 | E5: =MID(Q5,Hoja2!$D$6,Hoja2!$B$6) -> 38000275 | F5: =MID(Q5,Hoja2!$D$7,Hoja2!$B$7) -> 060098 | G5: =MID(Q5,Hoja2!$D$8,Hoja2!$B$8)/100 -> 2031.88 | H5: =MID(Q5,Hoja2!$D$9,Hoja2!$B$9)/100 -> 10405.59 | I5: =MID(Q5,Hoja2!$D$10,Hoja2!$B$10)/100 -> 12437.47 | J5: =MID(Q5,Hoja2!$D$11,Hoja2!$B$11)/100 -> 1873.01 | K5: =MID(Q5,Hoja2!$D$12,Hoja2!$B$12) -> D | L5: =MID(Q5,Hoja2!$D$13,Hoja2!$B$13) -> 00000000000000 | M5: =MID(Q5,Hoja2!$D$14,Hoja2!$B$14)/100 -> 10564.46 | N5: =MID(Q5,Hoja2!$D$15,Hoja2!$B$15) -> 150811 | O5: =MID(Q5,Hoja2!$D$16,Hoja2!$B$16) -> 27272839900 | P5: =MID(Q5,Hoja2!$D$17,Hoja2!$B$17) -> M | Q5: TORRES ROSALIA VERONICA 2728399038242091343800027506009800000000203188000000010405590000000124374700000000187301D000000000000000000000105644615081127272839900M00000000000000
A6: =MID(Q6,Hoja2!$D$2,Hoja2!$F$2) -> RUIZ,GRACIELA MABEL | B6: =MID(Q6,Hoja2!$D$3,Hoja2!$B$3) -> 25837711 | C6: =MID(Q6,Hoja2!$D$4,Hoja2!$B$4) -> 38192 | D6: =MID(Q6,Hoja2!$D$5,Hoja2!$B$5) -> 04187 | E6: =MID(Q6,Hoja2!$D$6,Hoja2!$B$6) -> 38000534 | F6: =MID(Q6,Hoja2!$D$7,Hoja2!$B$7) -> 060098 | G6: =MID(Q6,Hoja2!$D$8,Hoja2!$B$8)/100 -> 1399.12 | H6: =MID(Q6,Hoja2!$D$9,Hoja2!$B$9)/100 -> 13448.63 | I6: =MID(Q6,Hoja2!$D$10,Hoja2!$B$10)/100 -> 14847.75 | J6: =MID(Q6,Hoja2!$D$11,Hoja2!$B$11)/100 -> 2420.75 | K6: =MID(Q6,Hoja2!$D$12,Hoja2!$B$12) -> D | L6: =MID(Q6,Hoja2!$D$13,Hoja2!$B$13) -> 00000000000000 | M6: =MID(Q6,Hoja2!$D$14,Hoja2!$B$14)/100 -> 12427 | N6: =MID(Q6,Hoja2!$D$15,Hoja2!$B$15) -> 110504 | O6: =MID(Q6,Hoja2!$D$16,Hoja2!$B$16) -> 27258377112 | P6: =MID(Q6,Hoja2!$D$17,Hoja2!$B$17) -> M | Q6: RUIZ,GRACIELA MABEL 2583771138192041873800053406009800000000139912000000013448630000000148477500000000242075D000000000000000000000124270011050427258377112M00000000000000
A7: =MID(Q7,Hoja2!$D$2,Hoja2!$F$2) -> SEQUEIRA LILIANA DEL VALL | B7: =MID(Q7,Hoja2!$D$3,Hoja2!$B$3) -> 30318111 | C7: =MID(Q7,Hoja2!$D$4,Hoja2!$B$4) -> 38257 | D7: =MID(Q7,Hoja2!$D$5,Hoja2!$B$5) -> 10605 | E7: =MID(Q7,Hoja2!$D$6,Hoja2!$B$6) -> 38000555 | F7: =MID(Q7,Hoja2!$D$7,Hoja2!$B$7) -> 060098 | G7: =MID(Q7,Hoja2!$D$8,Hoja2!$B$8)/100 -> 1401.03 | H7: =MID(Q7,Hoja2!$D$9,Hoja2!$B$9)/100 -> 14462.97 | I7: =MID(Q7,Hoja2!$D$10,Hoja2!$B$10)/100 -> 15864 | J7: =MID(Q7,Hoja2!$D$11,Hoja2!$B$11)/100 -> 2603.34 | K7: =MID(Q7,Hoja2!$D$12,Hoja2!$B$12) -> D | L7: =MID(Q7,Hoja2!$D$13,Hoja2!$B$13) -> 00000000000000 | M7: =MID(Q7,Hoja2!$D$14,Hoja2!$B$14)/100 -> 13260.66 | N7: =MID(Q7,Hoja2!$D$15,Hoja2!$B$15) -> 140112 | O7: =MID(Q7,Hoja2!$D$16,Hoja2!$B$16) -> 23303181113 | P7: =MID(Q7,Hoja2!$D$17,Hoja2!$B$17) -> M | Q7: SEQUEIRA LILIANA DEL VALL3031811138257106053800055506009800000000140103000000014462970000000158640000000000260334D000000000000000000000132606614011223303181113M00000000000000
A8: =MID(Q8,Hoja2!$D$2,Hoja2!$F$2) -> VARGAS,SILVIA SUSANA | B8: =MID(Q8,Hoja2!$D$3,Hoja2!$B$3) -> 21039406 | C8: =MID(Q8,Hoja2!$D$4,Hoja2!$B$4) -> 38192 | D8: =MID(Q8,Hoja2!$D$5,Hoja2!$B$5) -> 04214 | E8: =MID(Q8,Hoja2!$D$6,Hoja2!$B$6) -> 38000631 | F8: =MID(Q8,Hoja2!$D$7,Hoja2!$B$7) -> 060098 | G8: =MID(Q8,Hoja2!$D$8,Hoja2!$B$8)/100 -> 1468.4 | H8: =MID(Q8,Hoja2!$D$9,Hoja2!$B$9)/100 -> 13292.97 | I8: =MID(Q8,Hoja2!$D$10,Hoja2!$B$10)/100 -> 14761.37 | J8: =MID(Q8,Hoja2!$D$11,Hoja2!$B$11)/100 -> 2525.67 | K8: =MID(Q8,Hoja2!$D$12,Hoja2!$B$12) -> D | L8: =MID(Q8,Hoja2!$D$13,Hoja2!$B$13) -> 00000000000000 | M8: =MID(Q8,Hoja2!$D$14,Hoja2!$B$14)/100 -> 12235.7 | N8: =MID(Q8,Hoja2!$D$15,Hoja2!$B$15) -> 280392 | O8: =MID(Q8,Hoja2!$D$16,Hoja2!$B$16) -> 27210394066 | P8: =MID(Q8,Hoja2!$D$17,Hoja2!$B$17) -> M | Q8: VARGAS,SILVIA SUSANA 2103940638192042143800063106009800000000146840000000013292970000000147613700000000252567D000000000000000000000122357028039227210394066M00000000000000
A9: =MID(Q9,Hoja2!$D$2,Hoja2!$F$2) -> CORONEL,SUSANA ELIZABETH | B9: =MID(Q9,Hoja2!$D$3,Hoja2!$B$3) -> 27392181 | C9: =MID(Q9,Hoja2!$D$4,Hoja2!$B$4) -> 38257 | D9: =MID(Q9,Hoja2!$D$5,Hoja2!$B$5) -> 11721 | E9: =MID(Q9,Hoja2!$D$6,Hoja2!$B$6) -> 38000665 | F9: =MID(Q9,Hoja2!$D$7,Hoja2!$B$7) -> 060098 | G9: =MID(Q9,Hoja2!$D$8,Hoja2!$B$8)/100 -> 1329.83 | H9: =MID(Q9,Hoja2!$D$9,Hoja2!$B$9)/100 -> 12435.48 | I9: =MID(Q9,Hoja2!$D$10,Hoja2!$B$10)/100 -> 13765.31 | J9: =MID(Q9,Hoja2!$D$11,Hoja2!$B$11)/100 -> 2238.38 | K9: =MID(Q9,Hoja2!$D$12,Hoja2!$B$12) -> D | L9: =MID(Q9,Hoja2!$D$13,Hoja2!$B$13) -> 00000000000000 | M9: =MID(Q9,Hoja2!$D$14,Hoja2!$B$14)/100 -> 11526.93 | N9: =MID(Q9,Hoja2!$D$15,Hoja2!$B$15) -> 250603 | O9: =MID(Q9,Hoja2!$D$16,Hoja2!$B$16) -> 27273921813 | P9: =MID(Q9,Hoja2!$D$17,Hoja2!$B$17) -> M | Q9: CORONEL,SUSANA ELIZABETH 2739218138257117213800066506009800000000132983000000012435480000000137653100000000223838D000000000000000000000115269325060327273921813M00000000000000
A10: =MID(Q10,Hoja2!$D$2,Hoja2!$F$2) -> VALDEZ JOSE RAMON | B10: =MID(Q10,Hoja2!$D$3,Hoja2!$B$3) -> 28724181 | C10: =MID(Q10,Hoja2!$D$4,Hoja2!$B$4) -> 38613 | D10: =MID(Q10,Hoja2!$D$5,Hoja2!$B$5) -> 09134 | E10: =MID(Q10,Hoja2!$D$6,Hoja2!$B$6) -> 38000801 | F10: =MID(Q10,Hoja2!$D$7,Hoja2!$B$7) -> 060098 | G10: =MID(Q10,Hoja2!$D$8,Hoja2!$B$8)/100 -> 1156.62 | H10: =MID(Q10,Hoja2!$D$9,Hoja2!$B$9)/100 -> 9898.42 | I10: =MID(Q10,Hoja2!$D$10,Hoja2!$B$10)/100 -> 11055.04 | J10: =MID(Q10,Hoja2!$D$11,Hoja2!$B$11)/100 -> 1781.71 | K10: =MID(Q10,Hoja2!$D$12,Hoja2!$B$12) -> D | L10: =MID(Q10,Hoja2!$D$13,Hoja2!$B$13) -> 00000000000000 | M10: =MID(Q10,Hoja2!$D$14,Hoja2!$B$14)/100 -> 9273.33 | N10: =MID(Q10,Hoja2!$D$15,Hoja2!$B$15) -> 281013 | O10: =MID(Q10,Hoja2!$D$16,Hoja2!$B$16) -> 20287241810 | P10: =MID(Q10,Hoja2!$D$17,Hoja2!$B$17) -> V | Q10: VALDEZ JOSE RAMON 2872418138613091343800080106009800000000115662000000009898420000000110550400000000178171D000000000000000000000092733328101320287241810V00000000000000
A11: =MID(Q11,Hoja2!$D$2,Hoja2!$F$2) -> ORELLANA SONIA MERCEDES | B11: =MID(Q11,Hoja2!$D$3,Hoja2!$B$3) -> 29613183 | C11: =MID(Q11,Hoja2!$D$4,Hoja2!$B$4) -> 38257 | D11: =MID(Q11,Hoja2!$D$5,Hoja2!$B$5) -> 10161 | E11: =MID(Q11,Hoja2!$D$6,Hoja2!$B$6) -> 38000843 | F11: =MID(Q11,Hoja2!$D$7,Hoja2!$B$7) -> 060098 | G11: =MID(Q11,Hoja2!$D$8,Hoja2!$B$8)/100 -> 2309.02 | H11: =MID(Q11,Hoja2!$D$9,Hoja2!$B$9)/100 -> 14462.97 | I11: =MID(Q11,Hoja2!$D$10,Hoja2!$B$10)/100 -> 16771.99 | J11: =MID(Q11,Hoja2!$D$11,Hoja2!$B$11)/100 -> 2603.34 | K11: =MID(Q11,Hoja2!$D$12,Hoja2!$B$12) -> D | L11: =MID(Q11,Hoja2!$D$13,Hoja2!$B$13) -> 00000000000000 | M11: =MID(Q11,Hoja2!$D$14,Hoja2!$B$14)/100 -> 14168.65 | N11: =MID(Q11,Hoja2!$D$15,Hoja2!$B$15) -> 290812 | O11: =MID(Q11,Hoja2!$D$16,Hoja2!$B$16) -> 27296131836 | P11: =MID(Q11,Hoja2!$D$17,Hoja2!$B$17) -> M | Q11: ORELLANA SONIA MERCEDES 2961318338257101613800084306009800000000230902000000014462970000000167719900000000260334D000000000000000000000141686529081227296131836M00000000000000
A12: =MID(Q12,Hoja2!$D$2,Hoja2!$F$2) -> JAIMES,CLAUDIA NATALI | B12: =MID(Q12,Hoja2!$D$3,Hoja2!$B$3) -> 32685653 | C12: =MID(Q12,Hoja2!$D$4,Hoja2!$B$4) -> 38265 | D12: =MID(Q12,Hoja2!$D$5,Hoja2!$B$5) -> 50057 | E12: =MID(Q12,Hoja2!$D$6,Hoja2!$B$6) -> 38001132 | F12: =MID(Q12,Hoja2!$D$7,Hoja2!$B$7) -> 060098 | G12: =MID(Q12,Hoja2!$D$8,Hoja2!$B$8)/100 -> 1997.23 | H12: =MID(Q12,Hoja2!$D$9,Hoja2!$B$9)/100 -> 9898.42 | I12: =MID(Q12,Hoja2!$D$10,Hoja2!$B$10)/100 -> 11895.65 | J12: =MID(Q12,Hoja2!$D$11,Hoja2!$B$11)/100 -> 1781.71 | K12: =MID(Q12,Hoja2!$D$12,Hoja2!$B$12) -> D | L12: =MID(Q12,Hoja2!$D$13,Hoja2!$B$13) -> 00000000000000 | M12: =MID(Q12,Hoja2!$D$14,Hoja2!$B$14)/100 -> 10113.94 | N12: =MID(Q12,Hoja2!$D$15,Hoja2!$B$15) -> 020513 | O12: =MID(Q12,Hoja2!$D$16,Hoja2!$B$16) -> 27326856539 | P12: =MID(Q12,Hoja2!$D$17,Hoja2!$B$17) -> M | Q12: JAIMES,CLAUDIA NATALI 3268565338265500573800113206009800000000199723000000009898420000000118956500000000178171D000000000000000000000101139402051327326856539M00000000000000
A13: =MID(Q13,Hoja2!$D$2,Hoja2!$F$2) -> VILLALBA,EVA EDIT | B13: =MID(Q13,Hoja2!$D$3,Hoja2!$B$3) -> 23017815 | C13: =MID(Q13,Hoja2!$D$4,Hoja2!$B$4) -> 38184 | D13: =MID(Q13,Hoja2!$D$5,Hoja2!$B$5) -> 02045 | E13: =MID(Q13,Hoja2!$D$6,Hoja2!$B$6) -> 38001433 | F13: =MID(Q13,Hoja2!$D$7,Hoja2!$B$7) -> 060098 | G13: =MID(Q13,Hoja2!$D$8,Hoja2!$B$8)/100 -> 1156.62 | H13: =MID(Q13,Hoja2!$D$9,Hoja2!$B$9)/100 -> 9898.42 | I13: =MID(Q13,Hoja2!$D$10,Hoja2!$B$10)/100 -> 11055.04 | J13: =MID(Q13,Hoja2!$D$11,Hoja2!$B$11)/100 -> 1781.71 | K13: =MID(Q13,Hoja2!$D$12,Hoja2!$B$12) -> D | L13: =MID(Q13,Hoja2!$D$13,Hoja2!$B$13) -> 00000000000000 | M13: =MID(Q13,Hoja2!$D$14,Hoja2!$B$14)/100 -> 9273.33 | N13: =MID(Q13,Hoja2!$D$15,Hoja2!$B$15) -> 180413 | O13: =MID(Q13,Hoja2!$D$16,Hoja2!$B$16) -> 27230178157 | P13: =MID(Q13,Hoja2!$D$17,Hoja2!$B$17) -> M | Q13: VILLALBA,EVA EDIT 2301781538184020453800143306009800000000115662000000009898420000000110550400000000178171D000000000000000000000092733318041327230178157M00000000000000
... A6152: =MID(Q6152,Hoja2!$D$2,Hoja2!$F$2) -> SALVATIERRA EMILCE CATALI | B6152: =MID(Q6152,Hoja2!$D$3,Hoja2!$B$3) -> 27392253 | C6152: =MID(Q6152,Hoja2!$D$4,Hoja2!$B$4) -> 59122 | D6152: =MID(Q6152,Hoja2!$D$5,Hoja2!$B$5) -> 80451 | E6152: =MID(Q6152,Hoja2!$D$6,Hoja2!$B$6) -> 59162072 | F6152: =MID(Q6152,Hoja2!$D$7,Hoja2!$B$7) -> 060714 | G6152: =MID(Q6152,Hoja2!$D$8,Hoja2!$B$8)/100 -> 1077.57 | H6152: =MID(Q6152,Hoja2!$D$9,Hoja2!$B$9)/100 -> 8741.17 | I6152: =MID(Q6152,Hoja2!$D$10,Hoja2!$B$10)/100 -> 9818.74 | J6152: =MID(Q6152,Hoja2!$D$11,Hoja2!$B$11)/100 -> 1573.41 | K6152: =MID(Q6152,Hoja2!$D$12,Hoja2!$B$12) -> D | L6152: =MID(Q6152,Hoja2!$D$13,Hoja2!$B$13) -> 00000000000000 | M6152: =MID(Q6152,Hoja2!$D$14,Hoja2!$B$14)/100 -> 8245.33 | N6152: =MID(Q6152,Hoja2!$D$15,Hoja2!$B$15) -> 011223 | O6152: =MID(Q6152,Hoja2!$D$16,Hoja2!$B$16) -> 27273922534 | P6152: =MID(Q6152,Hoja2!$D$17,Hoja2!$B$17) -> M | Q6152: SALVATIERRA EMILCE CATALI2739225359122804515916207206071400000000107757000000008741170000000098187400000000157341D000000000000000000000082453301122327273922534M00000000000000
G6153: =SUM(G2:G6152) -> 11027478 | H6153: =SUM(H2:H6152) -> 87939523 | I6153: =SUM(I2:I6152) -> 98967001 | J6153: =SUM(J2:J6152) -> 16139469 | M6153: =SUM(M2:M6152) -> 82827532

Sheet Hoja2
A1: COLUMNA | B1: LONG | C1: DEFECTO | D1: COMIENZA | E1: TERMINA | F1: LONG +1
A2: NOMBRE | B2: 25 | D2: 1 | F2: =B2 -> 25
A3: DNI | B3: 8 | D3: =D2+F2 -> 26 | F3: 9
A4: LUGAR DE PAGO | B4: 5 | D4: =D3+B3 -> 34 | F4: =B4 -> 5
A5: ESCUELA | B5: 5 | D5: =D4+B4 -> 39 | F5: =B5 -> 5
A6: CONTROL | B6: 8 | D6: =D5+B5 -> 44 | F6: =B6 -> 8
A7: CARGO | B7: 6 | D7: =D6+B6 -> 52 | F7: =B7 -> 6
A8: TOTAL HAB SIN APORTE | B8: 14 | D8: =D7+B7 -> 58 | F8: =B8 -> 14
A9: TOTAL HAB CON APORTE | B9: 14 | D9: =D8+B8 -> 72 | F9: =B9 -> 14
A10: TOTAL HABER | B10: 14 | D10: =D9+B9 -> 86 | F10: =B10 -> 14
A11: TOTAL DESCUENTOS | B11: 14 | D11: =D10+B10 -> 100 | F11: =B11 -> 14
A12: PLANTA | B12: 1 | D12: =D11+B11 -> 114 | F12: =B12 -> 1
A13: SALARIO | B13: 14 | C13: 000000000' | D13: =D12+B12 -> 115 | F13: =B13 -> 14
A14: TOTAL LIQUIDO | B14: 14 | D14: =D13+B13 -> 129 | F14: =B14 -> 14
A15: FECHA INGRESO | B15: 6 | D15: =D14+B14 -> 143 | F15: =B15 -> 6
A16: CUIL | B16: 11 | D16: =D15+B15 -> 149 | F16: =B16 -> 11
A17: SEXO | B17: 1 | D17: =D16+B16 -> 160 | F17: =B17 -> 1
